{"job title": "Business Data Analyst", "company": "Kforce", "city state": "\u2013 San Francisco, CA", "rating": "3.7", "job description": "<strong>RESPONSIBILITIES:</strong><br><br>Kforce has a client in search of a Business Data Analyst in San Francisco, California (CA).\n<br><br>\nSummary:\n<br>\nThe ideal candidate will be able to go through the Wholesale Data, make sure there's proper data lineage, data controls, data quality, and data usage overall. The Analyst will be supporting Wholesale data. Specific upgrades/initiatives to this project will be focused on security upgrades, and reporting analytics. Other responsibilities will include assessing reporting needs, grading reports, and being able to document data reports in SQL.<br><br><strong>REQUIREMENTS:</strong>\n\n<ul>\n<li> 5+ years of experience as a Business Data Analyst in an enterprise environment</li>\n\n<li> 3 years of experience with SQL (ability to retrieve group data, and perform data analysis)</li>\n\n<li> Good business analysis experience (Gap analysis, report design, and report development)</li>\n\n<li> Ability to write BRDs</li>\n</ul>\n\nPlusses:\n\n\n<ul>\n<li> Tableau experience</li>\n</ul>\n\nStart your career off on the right foot with one of 'America's Top 500 Companies', as awarded by Forbes. Our client is known as a place where people feel included, valued, supported and respected. Innovative thinking and industry-leading technology allow their associates to thrive and grow in their careers. And with a priority placed on their culture and company principles, their commitment to diversity, ethics and the communities in which they operate is their driving force. \n<br><br>\nKforce is an Equal Opportunity/Affirmative Action Employer. All qualified applicants will receive consideration for employment without regard to race, color, religion, sex, pregnancy, sexual orientation, gender identity, national origin, age, protected veteran status, or disability status."}