{"job title": "Data Engineer", "company": "Dropbox", "city state": "\u2013 San Francisco, CA", "rating": "4.2", "job description": "<strong>Company Description</strong>\n<br><br>\nDropbox is a leading global collaboration platform that's transforming the way people work together, from the smallest business to the largest enterprise. With more than 500 million registered users across more than 180 countries, our mission is to unleash the world's creative energy by designing a more enlightened way of working. Headquartered in San Francisco, CA, Dropbox has more than 12 offices around the world.\n<br><br>\nTeam Description\n<br><br>\nOur Business Strategy &amp; Operations team sets and drives key business initiatives across the company. We complement and support product, engineering, sales, and marketing teams across three critical areas: corporate and business unit strategy, business planning and sales operations, and business systems and tools development.\n<br><br>\nRole Description<br><br>SDL2017"}