{"job title": "Research Scientist", "company": "NSU (Nova Southeastern University)", "city state": "\u2013 Rumbaugh/Goodwin Institute, Plantation, FL 33313", "rating": "3.5", "job description": "<div>Position Information</div>\n<br>\n<div>\n<div> \nJob Title\n<br>\n\n<br>\n Research Scientist</div>\n<br>\n <div> \nPosition Number\n<br>\n\n<br>\n 992522</div>\n<br>\n <div> \nCenter\n<br>\n\n<br>\n HPD/RGI</div>\n<br>\n <div> \nLocation\n<br>\n\n<br>\n Rumbaugh/Goodwin Institute, Plantation, FL 33313</div>\n<br>\n <div> \nJob Open Date\n<br>\n\n<br>\n 03-20-2017</div>\n<br>\n <div> \nJob Close Date\n<br>\n\n<br>\n Open Until Filled</div> <div> \nJob Category\n<br>\n\n<br>\n Exempt</div>\n<br>\n <div> \n<strong>Hiring Range:</strong>\n<br>\n\n<br>\n Commensurate With Experience</div>\n<br>\n <div> \nPay Basis\n<br>\n\n<br>\n Annually</div>\n<br>\n <div> \n<strong>Subject to Grant Funding?:</strong>\n<br>\n\n<br>\n No</div>\n<br>\n <div> \n<strong>Job Grade/level:</strong>\n<br>\n\n<br>\n 57</div>\n<br>\n <div> \nType of Shift\n<br>\n\n<br>\n Non-Faculty Full time</div>\n<br>\n <div> \nBenefits Eligible\n<br>\n\n<br>\n Reg FT w/Benefits</div>\n<br>\n <div> \n<strong>Primary Purpose:</strong>\n<br>\n\n<br>\n Provide research services, grant writing and administrative support to Director of the Cancer Research Institute.</div>\n<br>\n <div> \n<strong>Essential Job Functions:</strong>\n\n\n<ul>\n<li>Conduct basic and applied research using cell culture, animal models and human cancer samples.</li>\n<li>Develop and write research proposals, submit grant applications and seek funding from both internal and external sources.</li>\n<li>Develop independent research, write and publish research articles, research reports, research protocols and abstracts from data collected and analyzed.</li>\n<li>Conduct drug discovery, cancer biomarkers or cancer genomics research.</li>\n<li>Mentor junior scientists and research assistants</li>\n<li>Prepare cells, plasma and other components from the blood samples, document details of the samples, store samples in liquid nitrogen, maintain inventory, prepare samples for shipment and shipping the samples.</li>\n<li>Handle animals for experiments, implanting tumors, measure tumor size, administer drugs and other experimental compounds and all other procedures that are required for completion of experiments.</li>\n<li>Perform cell culture of various cells including cancer cells, maintain the cells in culture, treat cells with drugs, prepare cell lysates for analysis and store cells in liquid nitrogen</li>\n<li>Develop recombinant DNAs, recombinant DNA derived products and engineer production of antibody and growth factors using recombinant DNA technology.</li>\n<li>Image mice, cells and other experimental subjects in the Night Owl imaging system, perform imaging using microscope imaging system, generate, analyze and interpret date from images.</li>\n<li>Immunize animals and produce antibodies, purify antibodies, tap mice for antibody production, collect cells from ascites to freeze or re-inject.</li>\n<li>Perform in vitro/in vivo cytotoxic assays, enzyme assays, drug screening, ELISA, PAGE, Western blots, Northern blots, Southern blots, PCR, RT-PCR, etc.</li>\n<li>Maintain the water purification system, incubators, liquid nitrogen tanks, freezers, refrigerators etc.</li>\n<li>Order, receive and maintain supplies, ensure appropriate inventory levels, maintain inventory</li>\n<li>Perform other duties as assigned.</li></ul></div>\n\n\n\n<strong></strong><div><strong> \nMarginal Job Functions:</strong>\n<br>\n\n<br>\n Supervise graduate and undergraduate students in the research laboratory.</div>\n<br>\n <div> \n<strong>Required Knowledge, Skills and Abilities:</strong>\n<br>\n\n<br>\n Knowledge and experience for conducting laboratory research.</div>\n<br>\n <div> \nJob Description</div>\n\n<br><div> \nJob Requirements</div>\n\n<br><div><strong>Required Certifications/Licensures:</strong></div><div> \nRequired Education\n<br>\n\n<br>\n Doctoral Degree</div>\n<br>\n <div> \n<strong>Major (if required):</strong>\n<br>\n\n<br>\n Biological Sciences or related field</div>\n<br>\n <div> \n<strong>Required Experience:</strong>\n<br>\n\n<br>\n Five (5) to 10 years research experience in a laboratory setting.</div>\n<br>\n <div> \n<strong>Preferred Qualifications:</strong>\n<br>\n\n<br>\n Existing Grant Funding</div>\n<br>\n <div> \nIs this a safety sensitive position (are applicants potentially subject to drug testing)?\n<br>\n\n<br>\n No</div>\n<br>\n <div> \nDoes this position require a criminal background screening?\n<br>\n\n<br>\n No</div>\n<br>\n <div> \nPre-Employment Conditions</div>\n\n<br><div> \nSensitivity Disclaimer</div>\n\n<br><div> \n<strong>Quick Link:</strong>\n<br>\n\n<br>\n www.nsujobs.com/applicants/Central?quickFind=80933</div>\n </div>\n\n<br>"}